Workbook

Sheet Overview
A1: YEPPER — AD SPACE PRICING (NEW MODEL)
A2: Web owners keep 100%. Yepper's margin is added ON TOP of what advertisers pay.
A4: HOW THE NEW MODEL WORKS
A5: 1. The listed price is the OWNER'S money | B5: Every price in this workbook is what the web owner receives in full. Yepper does not deduct anything from it.
A6: 2. Advertiser pays the price + 30% | B6: The system adds a 30% margin on top. Example: a 82,000 space → advertiser pays 106,600. The owner still receives the full 82,000; Yepper earns the 24,600 added on top.
A7: 3. Owner always receives 100% | B7: Unlike the old commission model (owner kept 70%), the owner now keeps the entire listed price. The margin is the advertiser's, not the owner's.
A8: 4. Margin can fall for top performers | B8: Yepper's added margin starts at 30%. For high-performing sites it can drop to 25% / 20% / 15%, making their spaces cheaper for advertisers — the owner still keeps 100% either way.
A9: 5. Multiple advertisers per space | B9: One space can be booked by several advertisers in rotation. Each pays the price + margin; the owner collects the full price from each.
A10: 6. Tiers by verified traffic | B10: Standard 10K–50K, Premium 50K–200K, Elite 200K+ monthly visitors (via Google Search Console). Smaller verified tiers: Starter, Basic. Unverified = 30-day, capped.
A11: MARGIN ADDED ON TOP (was commission)
A12: Stage | B12: Margin added on top → advertiser pays
A13: Starting (day one) | B13: +30% (owner keeps 100%)
A14: Good (6+ months active) | B14: +25% (owner keeps 100%)
A15: Excellent (high CTR) | B15: +20% (owner keeps 100%)
A16: Top performer | B16: +15% (owner keeps 100%)

Sheet Advertiser Pays (+30%)
A1: WHAT THE ADVERTISER PAYS — PRICE + 30% MARGIN (RWF)
A2: Each amount = the owner price x 1.30. The extra 30% is Yepper's margin; the owner still receives the full price shown on the previous sheet.
A4: Ad Space | B4: Description | C4: Visibility | D4: Unverified 30-day, 63K total | E4: Starter 500–2K/mo 20K total | F4: Basic 2K–10K/mo 100K total | G4: Standard 10K–50K/mo 210K total | H4: Premium 50K–200K/mo 575K total | I4: Elite 200K+/mo 1.5M total
A5: Header | B5: Banner ad space in the header section of the website | C5: Highest — top of every page | D5: ='Owner Earnings (100%)'!C5*1.3 -> 11700 | E5: ='Owner Earnings (100%)'!D5*1.3 -> 3900 | F5: ='Owner Earnings (100%)'!E5*1.3 -> 19500 | G5: ='Owner Earnings (100%)'!F5*1.3 -> 39000 | H5: ='Owner Earnings (100%)'!G5*1.3 -> 106600 | I5: ='Owner Earnings (100%)'!H5*1.3 -> 286000
A6: Above the Fold | B6: Prime visibility area at the top of webpage before scrolling | C6: Very high — before scroll | D6: ='Owner Earnings (100%)'!C6*1.3 -> 10140 | E6: ='Owner Earnings (100%)'!D6*1.3 -> 3380 | F6: ='Owner Earnings (100%)'!E6*1.3 -> 16900 | G6: ='Owner Earnings (100%)'!F6*1.3 -> 33800 | H6: ='Owner Earnings (100%)'!G6*1.3 -> 92300 | I6: ='Owner Earnings (100%)'!H6*1.3 -> 247000
A7: Sticky Sidebar | B7: Sidebar ad that stays visible as user scrolls | C7: High — follows scroll | D7: ='Owner Earnings (100%)'!C7*1.3 -> 7800 | E7: ='Owner Earnings (100%)'!D7*1.3 -> 2600 | F7: ='Owner Earnings (100%)'!E7*1.3 -> 13000 | G7: ='Owner Earnings (100%)'!F7*1.3 -> 26000 | H7: ='Owner Earnings (100%)'!G7*1.3 -> 71500 | I7: ='Owner Earnings (100%)'!H7*1.3 -> 192400
A8: Mobile Interstitial | B8: Full-screen mobile ads that appear between content | C8: High — full screen mobile | D8: ='Owner Earnings (100%)'!C8*1.3 -> 7800 | E8: ='Owner Earnings (100%)'!D8*1.3 -> 2600 | F8: ='Owner Earnings (100%)'!E8*1.3 -> 13000 | G8: ='Owner Earnings (100%)'!F8*1.3 -> 26000 | H8: ='Owner Earnings (100%)'!G8*1.3 -> 71500 | I8: ='Owner Earnings (100%)'!H8*1.3 -> 192400
A9: Overlay | B9: Ad that overlays on top of page content | C9: High — covers content | D9: ='Owner Earnings (100%)'!C9*1.3 -> 7020 | E9: ='Owner Earnings (100%)'!D9*1.3 -> 2340 | F9: ='Owner Earnings (100%)'!E9*1.3 -> 11700 | G9: ='Owner Earnings (100%)'!F9*1.3 -> 23400 | H9: ='Owner Earnings (100%)'!G9*1.3 -> 63700 | I9: ='Owner Earnings (100%)'!H9*1.3 -> 171600
A10: Floating | B10: Ads that float over page content, follows user scrolling | C10: Medium-high — follows user | D10: ='Owner Earnings (100%)'!C10*1.3 -> 6240 | E10: ='Owner Earnings (100%)'!D10*1.3 -> 2080 | F10: ='Owner Earnings (100%)'!E10*1.3 -> 10400 | G10: ='Owner Earnings (100%)'!F10*1.3 -> 20800 | H10: ='Owner Earnings (100%)'!G10*1.3 -> 57200 | I10: ='Owner Earnings (100%)'!H10*1.3 -> 153400
A11: Modal | B11: Pop-up ad that appears in a modal window | C11: Medium-high — interrupts | D11: ='Owner Earnings (100%)'!C11*1.3 -> 5460 | E11: ='Owner Earnings (100%)'!D11*1.3 -> 1820 | F11: ='Owner Earnings (100%)'!E11*1.3 -> 9100 | G11: ='Owner Earnings (100%)'!F11*1.3 -> 18200 | H11: ='Owner Earnings (100%)'!G11*1.3 -> 49400 | I11: ='Owner Earnings (100%)'!H11*1.3 -> 132600
A12: Left Rail | B12: Ad space along the left side of the webpage | C12: Medium — standard sidebar | D12: ='Owner Earnings (100%)'!C12*1.3 -> 4680 | E12: ='Owner Earnings (100%)'!D12*1.3 -> 1560 | F12: ='Owner Earnings (100%)'!E12*1.3 -> 7800 | G12: ='Owner Earnings (100%)'!F12*1.3 -> 15600 | H12: ='Owner Earnings (100%)'!G12*1.3 -> 42900 | I12: ='Owner Earnings (100%)'!H12*1.3 -> 114400
A13: Right Rail | B13: Ad space along the right side of the webpage | C13: Medium — standard sidebar | D13: ='Owner Earnings (100%)'!C13*1.3 -> 4680 | E13: ='Owner Earnings (100%)'!D13*1.3 -> 1560 | F13: ='Owner Earnings (100%)'!E13*1.3 -> 7800 | G13: ='Owner Earnings (100%)'!F13*1.3 -> 15600 | H13: ='Owner Earnings (100%)'!G13*1.3 -> 42900 | I13: ='Owner Earnings (100%)'!H13*1.3 -> 114400
A14: Sidebar | B14: Ad placement in the website sidebar | C14: Medium — common placement | D14: ='Owner Earnings (100%)'!C14*1.3 -> 3900 | E14: ='Owner Earnings (100%)'!D14*1.3 -> 1300 | F14: ='Owner Earnings (100%)'!E14*1.3 -> 6500 | G14: ='Owner Earnings (100%)'!F14*1.3 -> 13000 | H14: ='Owner Earnings (100%)'!G14*1.3 -> 35100 | I14: ='Owner Earnings (100%)'!H14*1.3 -> 94900
A15: In Feed (Native) | B15: Native ad placement within content feeds | C15: Medium — native, in body | D15: ='Owner Earnings (100%)'!C15*1.3 -> 3120 | E15: ='Owner Earnings (100%)'!D15*1.3 -> 1040 | F15: ='Owner Earnings (100%)'!E15*1.3 -> 5200 | G15: ='Owner Earnings (100%)'!F15*1.3 -> 10400 | H15: ='Owner Earnings (100%)'!G15*1.3 -> 28600 | I15: ='Owner Earnings (100%)'!H15*1.3 -> 76700
A16: Inline Content | B16: Ad placement directly within article text | C16: Medium — mid-article | D16: ='Owner Earnings (100%)'!C16*1.3 -> 3120 | E16: ='Owner Earnings (100%)'!D16*1.3 -> 1040 | F16: ='Owner Earnings (100%)'!E16*1.3 -> 5200 | G16: ='Owner Earnings (100%)'!F16*1.3 -> 10400 | H16: ='Owner Earnings (100%)'!G16*1.3 -> 28600 | I16: ='Owner Earnings (100%)'!H16*1.3 -> 76700
... A19: Bottom | B19: Ad placement at the bottom of the webpage | C19: Lowest — end of page | D19: ='Owner Earnings (100%)'!C19*1.3 -> 1560 | E19: ='Owner Earnings (100%)'!D19*1.3 -> 520 | F19: ='Owner Earnings (100%)'!E19*1.3 -> 2600 | G19: ='Owner Earnings (100%)'!F19*1.3 -> 5200 | H19: ='Owner Earnings (100%)'!G19*1.3 -> 14300 | I19: ='Owner Earnings (100%)'!H19*1.3 -> 37700

Sheet Video Formats (movie)
A1: MOVIE-SITE VIDEO AD FORMATS (RWF) — RECOMMENDED
A2: Owner keeps 100% (blue = recommended inputs, change freely). Advertiser columns = owner × 1.30. Only Standard/Premium/Elite shown — the tiers movie sites realistically reach.
A4: Video Format | B4: When it shows | C4: Basis | D4: Owner: Standard | E4: Owner: Premium | F4: Owner: Elite | G4: Adv +30%: Standard | H4: Adv +30%: Premium | I4: Adv +30%: Elite
A5: Pre-roll | B5: Before the film starts (15–30s) | C5: Header × 1.25 | D5: 38000 | E5: 102000 | F5: 275000 | G5: =D5*1.3 -> 49400 | H5: =E5*1.3 -> 132600 | I5: =F5*1.3 -> 357500
A6: Mid-roll | B6: Inside the film, ~2× (unskippable) | C6: Header × 1.5 | D6: 45000 | E6: 123000 | F6: 330000 | G6: =D6*1.3 -> 58500 | H6: =E6*1.3 -> 159900 | I6: =F6*1.3 -> 429000
A7: Pause ad | B7: When the viewer pauses | C7: Header × 0.55 | D7: 17000 | E7: 45000 | F7: 121000 | G7: =D7*1.3 -> 22100 | H7: =E7*1.3 -> 58500 | I7: =F7*1.3 -> 157300
A8: Movie sponsorship | B8: Whole film / series (premium) | C8: Header × 4 (per film) | D8: 120000 | E8: 328000 | F8: 880000 | G8: =D8*1.3 -> 156000 | H8: =E8*1.3 -> 426400 | I8: =F8*1.3 -> 1144000
A10: Sponsorship is priced per film. A multi-film series is sold as a package (per-film × number of films, usually with a discount).

Sheet Owner Earnings (100%)
A1: WHAT THE WEB OWNER RECEIVES — FULL, PER MONTH (RWF)
A2: Owner keeps 100% of these amounts. Per ad space, per advertiser. Multiple advertisers can share a space in rotation.
A4: Ad Space | B4: Visibility | C4: Unverified | D4: Starter | E4: Basic | F4: Standard | G4: Premium | H4: Elite
A5: Header | B5: Highest — top of every page | C5: 9000 | D5: 3000 | E5: 15000 | F5: 30000 | G5: 82000 | H5: 220000
A6: Above the Fold | B6: Very high — before scroll | C6: 7800 | D6: 2600 | E6: 13000 | F6: 26000 | G6: 71000 | H6: 190000
A7: Sticky Sidebar | B7: High — follows scroll | C7: 6000 | D7: 2000 | E7: 10000 | F7: 20000 | G7: 55000 | H7: 148000
A8: Mobile Interstitial | B8: High — full screen mobile | C8: 6000 | D8: 2000 | E8: 10000 | F8: 20000 | G8: 55000 | H8: 148000
A9: Overlay | B9: High — covers content | C9: 5400 | D9: 1800 | E9: 9000 | F9: 18000 | G9: 49000 | H9: 132000
A10: Floating | B10: Medium-high — follows user | C10: 4800 | D10: 1600 | E10: 8000 | F10: 16000 | G10: 44000 | H10: 118000
A11: Modal | B11: Medium-high — interrupts | C11: 4200 | D11: 1400 | E11: 7000 | F11: 14000 | G11: 38000 | H11: 102000
A12: Left Rail | B12: Medium — standard sidebar | C12: 3600 | D12: 1200 | E12: 6000 | F12: 12000 | G12: 33000 | H12: 88000
A13: Right Rail | B13: Medium — standard sidebar | C13: 3600 | D13: 1200 | E13: 6000 | F13: 12000 | G13: 33000 | H13: 88000
A14: Sidebar | B14: Medium — common placement | C14: 3000 | D14: 1000 | E14: 5000 | F14: 10000 | G14: 27000 | H14: 73000
A15: In Feed (Native) | B15: Medium — native, in body | C15: 2400 | D15: 800 | E15: 4000 | F15: 8000 | G15: 22000 | H15: 59000
A16: Inline Content | B16: Medium — mid-article | C16: 2400 | D16: 800 | E16: 4000 | F16: 8000 | G16: 22000 | H16: 59000
... A19: Bottom | B19: Lowest — end of page | C19: 1200 | D19: 400 | E19: 2000 | F19: 4000 | G19: 11000 | H19: 29000
